guangbo/__init__.py
guangbo/config.py
guangbo/core.py
guangbo-0.1.0.dist-info/licenses/LICENSE
guangbo-0.1.0.dist-info/METADATA
guangbo-0.1.0.dist-info/WHEEL
guangbo-0.1.0.dist-info/top_level.txt
guangbo-0.1.0.dist-info/RECORD
